promap/__init__.py
promap/__main__.py
promap/capture.py
promap/decode.py
promap/gray.py
promap/project.py
promap/reproject.py
promap-0.0.2.dist-info/LICENSE
promap-0.0.2.dist-info/METADATA
promap-0.0.2.dist-info/WHEEL
promap-0.0.2.dist-info/entry_points.txt
promap-0.0.2.dist-info/top_level.txt
promap-0.0.2.dist-info/RECORD
