Metadata-Version: 2.1
Name: promap
Version: 0.0.2
Summary: Projection mapping pipeline
Home-page: https://github.com/ervanalb/promap
Author: Eric Van Albert
Author-email: eric@van.al
License: UNKNOWN
Platform: UNKNOWN
Classifier: Programming Language :: Python :: 3
Classifier: License :: OSI Approved :: MIT License
Classifier: Operating System :: OS Independent
Requires-Dist: numpy
Requires-Dist: scipy
